Workbook

Sheet Assumptions
A1: Project Horizon — Business Case Assumptions
A2: Meridian Manufacturing & Logistics Pvt. Ltd. | WMS & Procurement Replacement
A5: Assumption | B5: Value | C5: Basis / Note
A6: Discount rate (WACC proxy) | B6: 0.12 | C6: Finance-provided hurdle rate for capex projects of this size
A7: Analysis period | B7: 5 | C7: Standard evaluation horizon for a mid-market platform decision
A8: Currency | B8: INR (₹ Lakh) | C8: 1 Lakh = ₹100,000; all figures below are in ₹ Lakh unless stated
A9: Blended finance labour cost | B9: 450 | C9: ₹ per hour, used to cost reconciliation effort (Finance interview)
A10: Warehouse downtime cost (peak week) | B10: 6.5 | C10: ₹ Lakh per unplanned outage during a peak dispatch week (Ops estimate)
A11: Current sustaining/workaround cost (status quo) | B11: 18 | C11: ₹ Lakh/year — IT contractor patches, manual reconciliation OT, paper forms/printing, spot-audit remediation
A13: All figures below are Business Analyst estimates built from stakeholder interviews (see Current-State Assessment) and indicative vendor pricing gathered during market scan; they are inputs for relative comparison, not vendor-quoted commercial offers.

Sheet Benefit Quantification
A1: Estimated Annual Benefit — Full System (Steady State)
A2: Applies once a replacement platform is fully live; used consistently across Build and Buy options
A5: Category | B5: Driver (from Current-State pain points) | C5: Baseline Cost/Risk Today (₹ Lakh/yr) | D5: Est. Annual Benefit (₹ Lakh/yr) | E5: Realized By | F5: Assumption / Method
A6: Finance reconciliation labour | B6: PP-03 | C6: 1.6 | D6: 1.3 | E6: All options | F6: 25 hrs/month saved x ₹450/hr x 12, less residual review effort
A7: Reduced stock-outs / expedited freight | B7: PP-01, PP-04 | C7: 32 | D7: 24 | E7: All options (full effect needs barcode) | F7: Ops estimate of annual expedite/air-freight spend triggered by inventory-visibility gaps; ~75% addressable
A8: Dispatch SLA / demurrage avoidance | B8: PP-05 | C8: 14 | D8: 10 | E8: All options | F8: Peak-week slowdowns causing missed dispatch windows, per logistics team's 2025 SLA breach log
A9: Warehouse labour productivity (barcode/handheld) | B9: PP-04 | C9: 20 | D9: 15 | E9: Vendors/Build with scanning module | F9: Reduced re-counts and pick errors; scaled down for options without native scanning support
A10: Procurement cycle time & invoice matching | B10: PP-06, PP-07 | C10: 9 | D10: 6 | E10: All options | F10: Faster PR-to-PO approval and 3-way match reduces processing hours and short-pay disputes
A11: Audit / compliance remediation | B11: PP-02, PP-09 | C11: 7 | D11: 5 | E11: All options | F11: Avoided cost of repeat internal-audit findings and manual evidence-gathering for SOX-style review
A12: IT unplanned-downtime avoidance | B12: PP-08 | C12: 13 | D12: 9 | E12: All options | F12: One fewer 12–14 hr peak-week outage per year, valued at downtime-cost assumption x hours
A13: Total | C13: =SUM(C6:C12) -> 96.6 | D13: =SUM(D6:D12) -> 70.3
A15: Note: StockFlow ERP-Lite (Vendor C) has no native barcode/scanning module, so the warehouse-labour-productivity line is reduced by 60% for that option on the Cost-Benefit Analysis tab — see Vendor Notes there.

Sheet Cost-Benefit Analysis
A1: Cost-Benefit Analysis — Status Quo vs. Build vs. Buy (3 Vendor Options)
A2: All figures ₹ Lakh. Negative = net cash outflow. Year 0 = implementation year.
A4: Line Item | B4: Status Quo (Do Nothing) | C4: Build In-House | D4: Vendor A — NexusWMS | E4: Vendor B — Warehouse360 | F4: Vendor C — StockFlow ERP-Lite
A5: Year 0 — Implementation / Capex Cost | B5: 0 | C5: -150 | D5: -40 | E5: -25 | F5: -12
A6: Annual Opex / Subscription (Yrs 1–5) | B6: -18 | C6: -35 | D6: -28 | E6: -18 | F6: -9
A7: Annual Benefit, Steady State (Yrs 2–5 / Yr 1 for vendors) | B7: 0 | C7: ='Benefit Quantification'!D13 -> 70.3 | D7: ='Benefit Quantification'!D13 -> 70.3 | E7: ='Benefit Quantification'!D13*0.94 -> 66.082 | F7: ='Benefit Quantification'!D13-('Benefit Quantification'!D9*0.6) -> 61.3
A9: Vendor Notes: Build In-House benefit phases in — only 40% realized in Year 1 (partial rollout) before reaching full run-rate in Year 2. Vendor B (Warehouse360) benefit is trimmed 6% for a lighter analytics module. Vendor C (StockFlow ERP-Lite) has no native barcode module, so 60% of the warehouse-labour-productivity benefit (row 9 on Benefit Quantification) is removed.
A11: Net Cash Flow by Year | B11: Status Quo (Do Nothing) | C11: Build In-House | D11: Vendor A — NexusWMS | E11: Vendor B — Warehouse360 | F11: Vendor C — StockFlow ERP-Lite
A12: Year 0 | B12: =B5 -> 0 | C12: =C5 -> -150 | D12: =D5 -> -40 | E12: =E5 -> -25 | F12: =F5 -> -12
A13: Year 1 | B13: =B6 -> -18 | C13: =C6+C7*0.4 -> -6.88 | D13: =D6+D7 -> 42.3 | E13: =E6+E7 -> 48.082 | F13: =F6+F7 -> 52.3
A14: Year 2 | B14: =B6 -> -18 | C14: =C6+C7 -> 35.3 | D14: =D6+D7 -> 42.3 | E14: =E6+E7 -> 48.082 | F14: =F6+F7 -> 52.3
A15: Year 3 | B15: =B6 -> -18 | C15: =C6+C7 -> 35.3 | D15: =D6+D7 -> 42.3 | E15: =E6+E7 -> 48.082 | F15: =F6+F7 -> 52.3
A16: Year 4 | B16: =B6 -> -18 | C16: =C6+C7 -> 35.3 | D16: =D6+D7 -> 42.3 | E16: =E6+E7 -> 48.082 | F16: =F6+F7 -> 52.3
A17: Year 5 | B17: =B6 -> -18 | C17: =C6+C7 -> 35.3 | D17: =D6+D7 -> 42.3 | E17: =E6+E7 -> 48.082 | F17: =F6+F7 -> 52.3
A19: Cumulative Net Cash Flow | B19: Status Quo (Do Nothing) | C19: Build In-House | D19: Vendor A — NexusWMS | E19: Vendor B — Warehouse360 | F19: Vendor C — StockFlow ERP-Lite
A20: Cumulative thru Yr 0 | B20: =B12 -> 0 | C20: =C12 -> -150 | D20: =D12 -> -40 | E20: =E12 -> -25 | F20: =F12 -> -12
A21: Cumulative thru Yr 1 | B21: =B20+B13 -> -18 | C21: =C20+C13 -> -156.88 | D21: =D20+D13 -> 2.3 | E21: =E20+E13 -> 23.082 | F21: =F20+F13 -> 40.3
A22: Cumulative thru Yr 2 | B22: =B21+B14 -> -36 | C22: =C21+C14 -> -121.58 | D22: =D21+D14 -> 44.6 | E22: =E21+E14 -> 71.164 | F22: =F21+F14 -> 92.6
A23: Cumulative thru Yr 3 | B23: =B22+B15 -> -54 | C23: =C22+C15 -> -86.28 | D23: =D22+D15 -> 86.9 | E23: =E22+E15 -> 119.246 | F23: =F22+F15 -> 144.9
A24: Cumulative thru Yr 4 | B24: =B23+B16 -> -72 | C24: =C23+C16 -> -50.98 | D24: =D23+D16 -> 129.2 | E24: =E23+E16 -> 167.328 | F24: =F23+F16 -> 197.2
A25: Cumulative thru Yr 5 | B25: =B24+B17 -> -90 | C25: =C24+C17 -> -15.68 | D25: =D24+D17 -> 171.5 | E25: =E24+E17 -> 215.41 | F25: =F24+F17 -> 249.5
A27: NPV @ discount rate (5-yr) | B27: =B12+NPV(Assumptions!$B$6,B13:B17) -> -64.885972 | C27: =C12+NPV(Assumptions!$B$6,C13:C17) -> -60.412114 | D27: =D12+NPV(Assumptions!$B$6,D13:D17) -> 112.48203 | E27: =E12+NPV(Assumptions!$B$6,E13:E17) -> 148.32485 | F27: =F12+NPV(Assumptions!$B$6,F13:F17) -> 176.5298
A28: Payback Period (years) | B28: =IF(B21>=0,ROUND(1+(-B20)/B13,1),IF(B22>=0,ROUND(2+(-B21)/B14,1),IF(B23>=0,ROUND(3+(-B22)/B15,1),IF(B24>=0,ROUND(4+(-B23)/B16,1),IF(B25>=0,ROUND(5+(-B24)/B17,1),"Beyond 5 yrs"))))) -> Beyond 5 yrs | C28: =IF(C21>=0,ROUND(1+(-C20)/C13,1),IF(C22>=0,ROUND(2+(-C21)/C14,1),IF(C23>=0,ROUND(3+(-C22)/C15,1),IF(C24>=0,ROUND(4+(-C23)/C16,1),IF(C25>=0,ROUND(5+(-C24)/C17,1),"Beyond 5 yrs"))))) -> Beyond 5 yrs | D28: =IF(D21>=0,ROUND(1+(-D20)/D13,1),IF(D22>=0,ROUND(2+(-D21)/D14,1),IF(D23>=0,ROUND(3+(-D22)/D15,1),IF(D24>=0,ROUND(4+(-D23)/D16,1),IF(D25>=0,ROUND(5+(-D24)/D17,1),"Beyond 5 yrs"))))) -> 1.9 | E28: =IF(E21>=0,ROUND(1+(-E20)/E13,1),IF(E22>=0,ROUND(2+(-E21)/E14,1),IF(E23>=0,ROUND(3+(-E22)/E15,1),IF(E24>=0,ROUND(4+(-E23)/E16,1),IF(E25>=0,ROUND(5+(-E24)/E17,1),"Beyond 5 yrs"))))) -> 1.5 | F28: =IF(F21>=0,ROUND(1+(-F20)/F13,1),IF(F22>=0,ROUND(2+(-F21)/F14,1),IF(F23>=0,ROUND(3+(-F22)/F15,1),IF(F24>=0,ROUND(4+(-F23)/F16,1),IF(F25>=0,ROUND(5+(-F24)/F17,1),"Beyond 5 yrs"))))) -> 1.2
A30: Blue figures are Business-Analyst inputs (implementation cost, opex, benefit adjustment factors). Black figures are formula outputs and will recalculate if any blue input changes.

Sheet Business Case Summary
A1: Business Case Summary — Project Horizon
A3: Problem
A4: LogiTrack Classic is a discontinued, single-server on-prem system carrying real business-continuity risk, and it forces Finance, Warehouse, and Procurement into manual, error-prone workarounds documented in the Current-State Assessment.
A6: Options considered
A7: Do nothing (absorb ongoing workaround cost and risk); build a custom platform in-house; or buy from one of three shortlisted vendors — NexusWMS (premium, cloud-native), Warehouse360 (mid-market), and StockFlow ERP-Lite (lower-cost, fewer modules).
A9: Recommendation
A10: Buy. Building in-house does not pay back inside the 5-year window (NPV of about -₹60 lakh at the 12% hurdle rate) because of the ₹150 lakh up-front build cost, the ongoing maintenance load and a partial-benefit first year; IT's own estimate is also an 18-month build with a small internal team, which adds delivery risk on top of the poor return. Among the three vendors, StockFlow ERP-Lite has the best NPV and payback on cost alone, but it has no native barcode module and so fails a mandatory requirement. Once the functional scorecard (Document 4) is applied, Warehouse360 gives the best balance of NPV, payback period and fit and is the recommended shortlist leader, with NexusWMS as the fallback if Warehouse360 does not clear the security and reference-check gate in due diligence.
A12: Key risk to flag
A13: All three vendor cost lines are Business-Analyst estimates from a market scan, not formal quotes — the RFP (Document 3) is the mechanism to get firm, comparable pricing before this business case is finalized for sign-off.
